aiohttp_tokenauth/__init__.py
aiohttp_tokenauth/middleware.py
aiohttp_tokenauth/utils.py
aiohttp_tokenauth-0.0.2.dist-info/LICENSE
aiohttp_tokenauth-0.0.2.dist-info/METADATA
aiohttp_tokenauth-0.0.2.dist-info/WHEEL
aiohttp_tokenauth-0.0.2.dist-info/top_level.txt
aiohttp_tokenauth-0.0.2.dist-info/RECORD
