Metadata-Version: 2.1
Name: aiohttp-tokenauth
Version: 0.0.2
Summary: Simple way to add token auth level in your aiohttp app
Home-page: https://github.com/madnesspie/aiohttp-tokenauth
Author: Alexander Polishchuk
Author-email: apolishchuk52@gmail.com
License: GNU General Public License v3 or later (GPLv3+)
Platform: POSIX
Classifier: Environment :: Web Environment
Classifier: Framework :: AsyncIO
Classifier: Programming Language :: Python
Classifier: Programming Language :: Python :: 3.6
Classifier: Programming Language :: Python :: 3.7
Classifier: Programming Language :: Python :: 3 :: Only
Classifier: Topic :: Internet :: WWW/HTTP
Classifier: Topic :: Internet :: WWW/HTTP :: Dynamic Content
Classifier: Intended Audience :: Developers
Classifier: Operating System :: Unix
Classifier: Programming Language :: Python :: 3
Classifier: Programming Language :: Python :: 3.6
Classifier: Programming Language :: Python :: 3.7
Requires-Dist: aiohttp
